HW4/GCD1.v
`timescale 1ns/10ps
module GCD_cntrl (idle, result_rdy, A_en, B_en, B_sel, clk, reset_, input_available, result_taken, B_zero, A_lt_B, A_sel , sub_op);
output reg idle, result_rdy, A_en, B_en, B_sel , sub_op; // sub_op:1 = B-A , 0=A-B;
input clk, reset_, input_available, result_taken, B_zero, A_lt_B;
output reg [1:0] A_sel ;

parameter WAIT = 2'd0, CALC = 2'd1, DONE = 2'd2;
parameter A_sel_In= 2'b00, A_sel_B=2'b01, A_sel_Sub=2'b10, A_sel_X=2'bxx;
parameter B_sel_In= 1'b0, B_sel_A= 1'b1, B_sel_X=1'bx;
parameter W = 16;

reg [1:0] next_state;
reg [1:0] state;

always @(*)
begin
next_state = state;
case ( state )
WAIT :
	if ( input_available )
		next_state = CALC;
CALC :
	if ( B_zero )
		next_state = DONE;
DONE :
	if ( result_taken )
		next_state = WAIT;
default:
	next_state = 2'bxx;
endcase
end

always @(posedge clk or negedge reset_)
	if(!reset_)
		state = WAIT ;
	else
		state = next_state ;

always @(*)
//Default control signals
begin
	A_sel = A_sel_X;
	A_en = 1'b0;
	B_sel = B_sel_X;
	B_en = 1'b0;
	idle = 1'b0;
	result_rdy = 1'b0;
	case ( state )
	WAIT: begin
		A_sel = A_sel_In;
		A_en = 1'b1;
		B_sel = B_sel_In;
		B_en = 1'b1;
		idle = 1'b1;
		end
	CALC: if ( A_lt_B ) begin
			A_sel = A_sel_Sub;
			sub_op = 1'b1;
			A_en = 1'b1;
			B_sel = B_sel_A;
			B_en = 1'b1;
			end
		else if ( !B_zero ) begin
			A_sel = A_sel_Sub;
			sub_op = 1'b0;
			A_en = 1'b1;
			end
	DONE: begin
		result_rdy = 1'b1;
		end
	endcase
end
endmodule

module GCDdatapath (clk, operand_A, operand_B, result_data, A_en, B_en, A_sel, B_sel, B_zero, A_lt_B , sub_op);
parameter A_sel_In= 2'b00;
parameter A_sel_B=2'b01;
parameter A_sel_Sub=2'b10;
parameter A_sel_X=2'bxx;
parameter B_sel_In= 1'b0;
parameter B_sel_A= 1'b1;
parameter B_sel_X=1'bx;
parameter W = 16;
input clk ;
// Data signals
input [W-1:0] operand_A, operand_B;
output [W-1:0] result_data;
// Control signals (ctrl->dpath)
input A_en, B_en , sub_op; // sub_op:1 = B-A , 0=A-B;
input [1:0] A_sel;
input B_sel;
// Control signals (dpath->ctrl)
output B_zero, A_lt_B;

reg [W-1:0] A_out;
reg [W-1:0] A;		
reg [W-1:0] B_out;
reg [W-1:0] B;
reg [W-1:0] tmp;
wire [W-1:0] sub_out;

always @(*)
	case (A_sel)
	A_sel_In: A_out = operand_A ;
	A_sel_B: A_out = B ;
	A_sel_Sub: A_out = sub_out;
	default: A_out = 16'bx ;
	endcase

always @(posedge clk)
	if (A_en)
		A = A_out;
		
always @(*)
	case(B_sel)
	B_sel_In: B_out = operand_B ;
	B_sel_A: B_out = A ;
	default: B_out = 16'bx ;
	endcase

always @(posedge clk)
	if (B_en)
		B = B_out ;
		
assign B_zero = (B==0);
assign A_lt_B = (A < B);
always @(*)
begin
	if(sub_op)
		tmp = B - A;
	else
		tmp = A - B;
end
assign sub_out = tmp;
assign result_data = A;
endmodule

module in_mdl (operand_A, operand_B, input_available, idle);
parameter W = 16;
output reg [W-1:0] operand_A, operand_B; 
output reg input_available;
input idle ;

initial
begin
	operand_A = 36;
	operand_B = 15;
	input_available = 1;
	#40
	input_available = 0;
end

always
	begin
	#40
	if (idle)
		begin
		operand_A = operand_A * 5;
		operand_B = operand_B * 2;
		input_available = 1;
		end
	else
		input_available = 0;
	end
endmodule
	
module out_mdl (result_data, result_rdy, result_taken);
parameter W = 16;
input [W-1:0] result_data;
input result_rdy;
output reg result_taken;

reg [W-1:0] result;

initial
result_taken = 0;

always @ (result_rdy)
	if (result_rdy)
		begin
		result = result_data;
		result_taken = 1 ;
		end
	else
		result_taken = 0 ;
endmodule

module testfixture ;
parameter W = 16;
//GCD instances
wire [1:0] A_sel ;
wire [W-1:0] operand_A, operand_B, result_data;

reg clk, reset_;

GCD_cntrl C1 (idle, result_rdy, A_en, B_en, B_sel, clk, reset_, input_available, result_taken, B_zero, A_lt_B, A_sel , sub_op) ;
GCDdatapath D1 (clk, operand_A, operand_B, result_data, A_en, B_en, A_sel, B_sel, B_zero, A_lt_B , sub_op) ;
in_mdl I1 (operand_A, operand_B, input_available, idle) ;
out_mdl O1(result_data, result_rdy, result_taken) ;
//Stimulus
initial
begin
	clk = 1'b0 ;
	repeat(80)
		#10 clk = ~clk ;
	$finish ;
end
	
initial
begin
  reset_ = 0;
  #15  reset_ = 1'b1;  
end


initial
begin
$dumpfile("GCD1.vcd");
$dumpvars;
end

endmodule

HW4/GCD1.vcd
$date
	Fri Jun 05 18:25:26 2020
$end
$version
	Icarus Verilog
$end
$timescale
	10ps
$end
$scope module testfixture $end
$var wire 1 ! sub_op $end
$var wire 1 " result_taken $end
$var wire 1 # result_rdy $end
$var wire 16 $ result_data [15:0] $end
$var wire 16 % operand_B [15:0] $end
$var wire 16 & operand_A [15:0] $end
$var wire 1 ' input_available $end
$var wire 1 ( idle $end
$var wire 1 ) B_zero $end
$var wire 1 * B_sel $end
$var wire 1 + B_en $end
$var wire 2 , A_sel [1:0] $end
$var wire 1 - A_lt_B $end
$var wire 1 . A_en $end
$var reg 1 / clk $end
$var reg 1 0 reset_ $end
$scope module C1 $end
$var wire 1 / clk $end
$var wire 1 0 reset_ $end
$var wire 1 " result_taken $end
$var wire 1 ' input_available $end
$var wire 1 ) B_zero $end
$var wire 1 - A_lt_B $end
$var reg 1 . A_en $end
$var reg 2 1 A_sel [1:0] $end
$var reg 1 + B_en $end
$var reg 1 * B_sel $end
$var reg 1 ( idle $end
$var reg 2 2 next_state [1:0] $end
$var reg 1 # result_rdy $end
$var reg 2 3 state [1:0] $end
$var reg 1 ! sub_op $end
$upscope $end
$scope module D1 $end
$var wire 1 . A_en $end
$var wire 2 4 A_sel [1:0] $end
$var wire 1 + B_en $end
$var wire 1 * B_sel $end
$var wire 1 / clk $end
$var wire 16 5 result_data [15:0] $end
$var wire 1 ! sub_op $end
$var wire 16 6 sub_out [15:0] $end
$var wire 16 7 operand_B [15:0] $end
$var wire 16 8 operand_A [15:0] $end
$var wire 1 ) B_zero $end
$var wire 1 - A_lt_B $end
$var reg 16 9 A [15:0] $end
$var reg 16 : A_out [15:0] $end
$var reg 16 ; B [15:0] $end
$var reg 16 < B_out [15:0] $end
$var reg 16 = tmp [15:0] $end
$upscope $end
$scope module I1 $end
$var wire 1 ( idle $end
$var reg 1 ' input_available $end
$var reg 16 > operand_A [15:0] $end
$var reg 16 ? operand_B [15:0] $end
$upscope $end
$scope module O1 $end
$var wire 16 @ result_data [15:0] $end
$var wire 1 # result_rdy $end
$var reg 16 A result [15:0] $end
$var reg 1 " result_taken $end
$upscope $end
$upscope $end
$enddefinitions $end
#0
$dumpvars
bx A
bx @
b1111 ?
b100100 >
bx =
b1111 <
bx ;
b100100 :
bx 9
b100100 8
b1111 7
bx 6
bx 5
b0 4
b0 3
b1 2
b0 1
00
0/
1.
x-
b0 ,
1+
0*
x)
1(
1'
b100100 &
b1111 %
bx $
0#
0"
x!
$end
#1000
b10101 6
b10101 =
1(
1+
0*
1.
b0 ,
b0 1
b0 4
b1 2
0-
b100100 $
b100100 5
b100100 @
b100100 9
0)
b1111 ;
1/
#1500
10
#2000
0/
#3000
bx <
b10101 :
0!
0(
0+
x*
1.
b10 ,
b10 1
b10 4
b1 3
1/
#4000
0/
0'
#5000
b110 :
b110 6
b110 =
b10101 $
b10101 5
b10101 @
b10101 9
1/
#6000
0/
#7000
b1001 :
b1001 6
b1001 =
b110 <
1+
1*
1!
1.
b10 ,
b10 1
b10 4
1-
b110 $
b110 5
b110 @
b110 9
1/
#8000
0/
#9000
b11 :
bx <
b11 6
b11 =
0!
0+
x*
1.
b10 ,
b10 1
b10 4
b1001 $
b1001 5
b1001 @
b1001 9
0-
b110 ;
1/
#10000
0/
#11000
b11 <
1+
1*
1!
1.
b10 ,
b10 1
b10 4
1-
b11 $
b11 5
b11 @
b11 9
1/
#12000
0/
#13000
b0 :
bx <
b0 6
b0 =
0!
0+
x*
1.
b10 ,
b10 1
b10 4
0-
b11 ;
1/
#14000
0/
#15000
b11 :
b11 6
b11 =
b0 <
1+
1*
1!
1.
b10 ,
b10 1
b10 4
1-
b0 $
b0 5
b0 @
b0 9
1/
#16000
0/
#17000
bx <
b1111111111111101 6
b1111111111111101 =
bx :
b10 2
0+
x*
0.
bx ,
bx 1
bx 4
b11 $
b11 5
b11 @
b11 9
1)
0-
b0 ;
1/
#18000
0/
#19000
b0 2
1"
b11 A
1#
b10 3
1/
#20000
0/
#21000
b1111 <
b100100 :
0"
1(
1+
0*
1.
b0 ,
b0 1
b0 4
0#
b0 3
1/
#22000
0/
#23000
1(
1+
0*
1.
b0 ,
b0 1
b0 4
b1111111111101011 6
b1111111111101011 =
0)
b1111 ;
b100100 $
b100100 5
b100100 @
b100100 9
1/
#24000
b1 2
b11110 <
b10110100 :
0/
1'
b11110 %
b11110 7
b11110 ?
b10110100 &
b10110100 8
b10110100 >
#25000
bx <
b10010110 :
0!
0(
0+
x*
1.
b10 ,
b10 1
b10 4
b10010110 6
b10010110 =
b1 3
b10110100 $
b10110100 5
b10110100 @
b10110100 9
b11110 ;
1/
#26000
0/
#27000
b1111000 :
b1111000 6
b1111000 =
b10010110 $
b10010110 5
b10010110 @
b10010110 9
1/
#28000
0/
0'
#29000
b1011010 :
b1011010 6
b1011010 =
b1111000 $
b1111000 5
b1111000 @
b1111000 9
1/
#30000
0/
#31000
b111100 :
b111100 6
b111100 =
b1011010 $
b1011010 5
b1011010 @
b1011010 9
1/
#32000
0/
#33000
b11110 :
b11110 6
b11110 =
b111100 $
b111100 5
b111100 @
b111100 9
1/
#34000
0/
#35000
b0 :
b0 6
b0 =
b11110 $
b11110 5
b11110 @
b11110 9
1/
#36000
0/
#37000
b11110 :
b11110 6
b11110 =
b0 <
1+
1*
1!
1.
b10 ,
b10 1
b10 4
1-
b0 $
b0 5
b0 @
b0 9
1/
#38000
0/
#39000
bx :
b10 2
b1111111111100010 6
b1111111111100010 =
bx <
0+
x*
0.
bx ,
bx 1
bx 4
1)
b0 ;
0-
b11110 $
b11110 5
b11110 @
b11110 9
1/
#40000
0/
#41000
b0 2
1"
b11110 A
1#
b10 3
1/
#42000
0/
#43000
b11110 <
b10110100 :
0"
1(
1+
0*
1.
b0 ,
b0 1
b0 4
0#
b0 3
1/
#44000
b1 2
b111100 <
b1110000100 :
0/
1'
b111100 %
b111100 7
b111100 ?
b1110000100 &
b1110000100 8
b1110000100 >
#45000
bx <
b1101001000 6
b1101001000 =
b1101001000 :
0!
0(
0+
x*
1.
b10 ,
b10 1
b10 4
b1 3
b1110000100 $
b1110000100 5
b1110000100 @
b1110000100 9
0)
0-
b111100 ;
1/
#46000
0/
#47000
b1100001100 :
b1100001100 6
b1100001100 =
b1101001000 $
b1101001000 5
b1101001000 @
b1101001000 9
1/
#48000
0/
0'
#49000
b1011010000 :
b1011010000 6
b1011010000 =
b1100001100 $
b1100001100 5
b1100001100 @
b1100001100 9
1/
#50000
0/
#51000
b1010010100 :
b1010010100 6
b1010010100 =
b1011010000 $
b1011010000 5
b1011010000 @
b1011010000 9
1/
#52000
0/
#53000
b1001011000 :
b1001011000 6
b1001011000 =
b1010010100 $
b1010010100 5
b1010010100 @
b1010010100 9
1/
#54000
0/
#55000
b1000011100 :
b1000011100 6
b1000011100 =
b1001011000 $
b1001011000 5
b1001011000 @
b1001011000 9
1/
#56000
0/
#57000
b111100000 :
b111100000 6
b111100000 =
b1000011100 $
b1000011100 5
b1000011100 @
b1000011100 9
1/
#58000
0/
#59000
b110100100 :
b110100100 6
b110100100 =
b111100000 $
b111100000 5
b111100000 @
b111100000 9
1/
#60000
0/
#61000
b101101000 :
b101101000 6
b101101000 =
b110100100 $
b110100100 5
b110100100 @
b110100100 9
1/
#62000
0/
#63000
b100101100 :
b100101100 6
b100101100 =
b101101000 $
b101101000 5
b101101000 @
b101101000 9
1/
#64000
0/
#65000
b11110000 :
b11110000 6
b11110000 =
b100101100 $
b100101100 5
b100101100 @
b100101100 9
1/
#66000
0/
#67000
b10110100 :
b10110100 6
b10110100 =
b11110000 $
b11110000 5
b11110000 @
b11110000 9
1/
#68000
0/
#69000
b1111000 :
b1111000 6
b1111000 =
b10110100 $
b10110100 5
b10110100 @
b10110100 9
1/
#70000
0/
#71000
b111100 :
b111100 6
b111100 =
b1111000 $
b1111000 5
b1111000 @
b1111000 9
1/
#72000
0/
#73000
b0 :
b0 6
b0 =
b111100 $
b111100 5
b111100 @
b111100 9
1/
#74000
0/
#75000
b111100 :
b111100 6
b111100 =
b0 <
1+
1*
1!
1.
b10 ,
b10 1
b10 4
1-
b0 $
b0 5
b0 @
b0 9
1/
#76000
0/
#77000
bx <
b1111111111000100 6
b1111111111000100 =
bx :
b10 2
0+
x*
0.
bx ,
bx 1
bx 4
b111100 $
b111100 5
b111100 @
b111100 9
1)
0-
b0 ;
1/
#78000
0/
#79000
b0 2
1"
b111100 A
1#
b10 3
1/
